run_with_coverage.py
run_with_coverage-0.1.0.dist-info/licenses/LICENSE
run_with_coverage-0.1.0.dist-info/METADATA
run_with_coverage-0.1.0.dist-info/WHEEL
run_with_coverage-0.1.0.dist-info/top_level.txt
run_with_coverage-0.1.0.dist-info/RECORD
