Metadata-Version: 2.4
Name: run-with-coverage
Version: 0.1.0
Summary: Run a Python script with coverage tracking and allow the user to specify the coverage data file.
Author-email: Jifeng Wu <jifengwu2k@gmail.com>
License-Expression: MIT
Project-URL: Homepage, https://github.com/jifengwu2k/run-with-coverage
Project-URL: Bug Tracker, https://github.com/jifengwu2k/run-with-coverage/issues
Classifier: Programming Language :: Python :: 3
Classifier: Operating System :: OS Independent
Requires-Python: >=3.6
License-File: LICENSE
Requires-Dist: coverage
Dynamic: license-file
